<annotation verified="yes">
	<folder>img</folder>
	<filename>EOJ6XC.jpg</filename>
	<path>D:\JakBikeHub\BIKE_HUB (Github)\Dockless\img\img\EOJ6XC.jpg</path>
	<source>
		<database>Unknown</database>
	</source>
	<size>
		<width>558</width>
		<height>313</height>
		<depth>3</depth>
	</size>
	<segmented>0</segmented>
	<object>
		<name>bike</name>
		<pose>Unspecified</pose>
		<truncated>0</truncated>
		<difficult>0</difficult>
		<bndbox>
			<xmin>177</xmin>
			<ymin>146</ymin>
			<xmax>227</xmax>
			<ymax>190</ymax>
		</bndbox>
	</object>
</annotation>
